cafy_deploy/__init__.py
cafy_deploy-0.0.1.dist-info/LICENSE
cafy_deploy-0.0.1.dist-info/METADATA
cafy_deploy-0.0.1.dist-info/WHEEL
cafy_deploy-0.0.1.dist-info/top_level.txt
cafy_deploy-0.0.1.dist-info/RECORD
