Metadata-Version: 2.1
Name: cafy-deploy
Version: 0.0.1
Summary: Cafy deployment
Home-page: https://cafy.io
Author: Amrendra Kumar
Author-email: kuamrend@cisco.com
License: UNKNOWN
Platform: UNKNOWN
Classifier: Programming Language :: Python :: 3
Classifier: License :: OSI Approved :: MIT License
Classifier: Operating System :: OS Independent
